Workbook

Sheet README
A1: Puente — Bank Partnership Target Tracker
A2: Prepared 12 August 2026. Companion to puente-bank-partnership-strategy.md
A4: HOW TO USE
A5: Fill only the yellow columns: Owner, Status, Last Contact, Next Step, Next Step Date, Notes.
A6: Everything else is research output — overwrite it if you learn better.
A7: Each target tab has one example row at the bottom showing the expected format. Delete it once you start.
A9: TABS
A10: Track 1 - Program Banks | B10: Banks already running fintech programs. Fastest route to live.
A11: Track 2 - Middleware | B11: BaaS platforms and infrastructure. Fastest to market, worse economics.
A12: Track 3 - CDFI MDI | B12: Mission-aligned institutions. Slower, durable, doubles as a fundraising asset.
A13: Do Not Approach | B13: Regulatory or viability problems. Documented so you don't rediscover them.
A14: Outreach Channels | B14: Accelerators, conferences, consultants and networks — your substitute for warm intros.
A15: First Call Questions | B15: The qualifying script. Ask these before investing time in any candidate.
A16: Dashboard | B16: Live counts by status. Formulas — do not overwrite.
A18: THE ONE RULE
A19: Ask the ITIN question on call one. No bank or platform publicly states its ITIN policy —
A20: not a single one in the entire research sweep. It cannot be screened in advance, and it is
A21: the thing most likely to end a conversation in month four instead of minute four.
A23: VERIFY BEFORE CONTACT
A24: Consent orders change monthly. Re-check each bank at orders.fdic.gov and apps.occ.gov/EASearch
A25: immediately before outreach. Do not rely on this file's Regulatory Status column alone.

Sheet Track 1 - Program Banks
A1: Institution | B1: Priority | C1: Location / Charter | D1: Why them — the hook to open with | E1: Deposit + Lending capability | F1: ITIN signal | G1: Regulatory status (VERIFY) | H1: How to make contact | I1: Owner | J1: Status | K1: Last Contact | L1: Next Step | M1: Next Step Date | N1: Notes
A2: Sunrise Banks, N.A. | B2: 1 - Lead | C2: St. Paul, MN · National (OCC) | D2: Issuing bank behind Self Financial's Credit Builder — 278,000+ loans / $249.7M originated in 2023. Structurally near-identical to Puente's mechanic. Open the email with this. | E2: Both. Fintech sponsor bank, Compliance-as-a-Service, and lending verticals. | F2: STRONG — runs Pathway2Home, an ITIN mortgage program for immigrants. CDFI certified, B Corp, GABV member. | G2: No consent order found (negative unverified — confirm via FDIC/OCC). | H2: Fintech partnerships form at sunrisebanks.com/fintech-partnerships · 844-786-5600 | J2: Not started
A3: Academy Bank | B3: 1 - Lead | C3: Kansas City, MO | D3: Powers Atlas (credit-building fintech) and BUILT ITIN onboarding workflows + a Spanish-language product version for it. Closest ITIN + secured-credit precedent found anywhere. | E3: Both. Tiered/partially-secured credit lines where a secured deposit unlocks a higher limit. | F3: STRONGEST FOUND — explicit ITIN workflows already built and in production for a comparable partner. | G3: None found. Publicly caps BaaS at 20% of deposits / 35% of revenue — disciplined, not distressed. | H3: Via academybank.com. Reference the Atlas partnership case study directly. | J3: Not started
A4: Continental Bank | B4: 1 - Lead | C4: Salt Lake City, UT · Utah industrial | D4: Local to you. Markets 120-day onboarding and 'direct access to decision-makers' — positioning aimed at smaller partners. Utah HQ is a legitimate warm-ish opener. | E4: Both, explicitly — deposit programs AND consumer revolving lines of credit. Exact product shape needed. | F4: Unknown — not publicly stated. Ask on call one. | G4: No consent order found. Small industrial bank — verify size via FDIC BankFind. | H4: cbankus.com/partnerships/fintech-strategic-partnerships · 15 W South Temple Ste 300, SLC | J4: Not started
A5: Thread Bank | B5: 2 - Strong | C5: Rogersville, TN | D5: FDIC consent order TERMINATED 22 Dec 2025 — clean now, and remediation is arguably a positive signal. Has a named SVP/Director of Fintech Partnerships (ex-Live Oak, ex-SVB). | E5: Deposit sweep / Program Bank network (IntraFi) plus fintech lending partnerships. Secured/credit-builder capability unconfirmed. | F5: Unknown. | G5: Order terminated Dec 2025. Ask what triggered it and what changed. | H5: thread.bank/connect-with-thread · customerservice@thread.bank | J5: Not started
A6: First Century Bank, N.A. | B6: 2 - Strong | C6: Tazewell, TN | D6: Also a Self Financial issuing bank — the literal product precedent exists here too. BUT likely conflicted with a direct competitor. | E6: Secured deposit collateralizing a credit-building facility, in production. | F6: Unknown. | G6: None found. | H6: firstcenturybank.com/contact. Raise the Self competitive-conflict question up front. | J6: Not started
A7: Coastal Community Bank (CCBX) | B7: 3 - Possible | C7: WA state charter | D7: Original BaaS pioneer, well-established program. Likely higher minimums than you want. | E7: Both, well established. | F7: Unknown. | G7: Self-identified a MATERIAL WEAKNESS in internal controls (Mar 2025) tied to BaaS partner loan accounting; restated 2023-24 financials. Says resolved. | H7: coastalbank.com | J7: Not started
A8: First Internet Bank | B8: 3 - Possible | C8: Fishers, IN | D8: Publishes thought-leadership on 'how to be a good sponsor bank' — a positive cultural signal — and a real partnership inbox, which is rare. | E8: General BaaS/embedded finance. Secured consumer credit unverified. | F8: Unknown. | G8: None found. | H8: fintech@firstinternetbank.com · 1-888-873-3424 | J8: Not started
A9: Column N.A. | B9: 3 - Possible | C9: San Francisco · National charter | D9: A chartered bank operating as a direct API. Healthiest financials in the sector (~$153M 2025 revenue, founder-owned, no outside investors). Confirmed RTP + FedNow. | E9: Both. Lending infra skews commercial/warehouse (Mercury, Brex). | F9: Unknown. | G9: None found. | H9: column.com · docs.column.com | J9: Not started
A10: Medallion Bank | B10: 3 - Possible | C10: Salt Lake City, UT | D10: Utah presence and actively signing new fintech consumer-lending partnerships as of May 2026. | E10: Consumer installment lending. Consumer FBO deposit capability UNCONFIRMED — key question. | F10: Unknown. | G10: None found. | H10: medallionbank.com | J10: Not started
A11: TAB Bank | B11: 3 - Possible | C11: Ogden, UT · Utah industrial | D11: Utah-based, publishes a dedicated FinTech Partners page. | E11: Card sponsorship + lending emphasized. Consumer FBO deposit unconfirmed. | F11: Unknown. | G11: None found. | H11: tabbank.com/fintech-partners · 1-800-355-3063 | J11: Not started
A12: Lead Bank | B12: 4 - Low | C12: Kansas City, MO | D12: Fast-growing (~$2.6B), ICONIQ-backed, direct API. But public positioning favors large established fintechs (Affirm, Ramp, Bridge). | E12: Both — FBO/virtual accounts, term loans and lines of credit. | F12: Unknown. | G12: No active order found. | H12: lead.bank — one exploratory call, don't over-invest. | J12: Not started
A13: FinWise Bank | B13: 4 - Low | C13: Sandy, UT | D13: YOU'VE ALREADY REACHED OUT. Likely a no on FIT, not compliance: their EVP publicly cites rejecting ~12-18 applicants per acceptance for being 'not big enough', and they've pivoted to ~90% commercial. | E13: Primarily lending origination programs, not deposit/BaaS. | F13: Unknown. | G13: No consent order found (positive). Facing data-breach litigation (~689K users). | H13: Already contacted — don't over-invest in follow-up. | J13: Not started
A14: EXAMPLE ROW - delete me | B14: 1 - Lead | C14: Anywhere, USA · State charter | D14: Example of the expected format — replace or delete this row once you start. | E14: Both. | F14: Unknown. | G14: Verified clean 12 Aug 2026. | H14: example@bank.com | I14: Joshua | J14: Not started | L14: Send intro email w/ Self precedent

Sheet Track 2 - Middleware
A1: Platform | B1: Priority | C1: What it is | D1: Why them — the hook | E1: Lending / secured credit support | F1: Instant rails (RTP/FedNow) | G1: Health signal | H1: How to make contact | I1: Owner | J1: Status | K1: Last Contact | L1: Next Step | M1: Next Step Date | N1: Notes
A2: Synctera | B2: 1 - Lead | C2: Full-stack BaaS | D2: BEST ARCHITECTURAL MATCH FOUND. Documents a CHARGE_SECURED primitive: an open-end credit account where a linked security deposit mechanically caps available credit. Fund $100 → $100 credit; spend $20 → both drop. That is your product. | E2: Yes — unsecured LOC plus the secured charge account. Sponsor bank is lender of record. | F2: UNVERIFIED — confirm on call. | G2: Raised $15M in 2026, expanding into Canada. Healthy. | H2: synctera.com · docs.synctera.com. ASK: can CHARGE_SECURED be decoupled from a card rail to fund a remittance? Does it furnish to bureaus? | J2: Not started
A3: Treasury Prime | B3: 1 - Lead | C3: Multi-bank BaaS | D3: Scale and regulatory credibility — $100B+ 2025 volume, 3M end-customer accounts, 100+ fintechs in production. GC testified to House Financial Services May 2026. Multi-bank routing is an explicit answer to Synapse's single-bank failure mode. | E3: Consumer lending APIs explicitly claimed. Secured structure unverified. | F3: UNVERIFIED. | G3: No confirmed raise since ~2023 — ask whether that's profitability or constraint. | H3: treasuryprime.com | J3: Not started
A4: Increase | B4: 2 - Rails | C4: Bank + API | D4: Not your lending partner — their credit products are institutional capital-call lines. But the ONLY transparent public pricing in the sector and a strong candidate for the settlement leg. | E4: No consumer secured credit found. | F4: YES — published at $2.50/txn for both RTP and FedNow origination. | G4: Own bank charter (Increase Bank), Forbes Fintech 50 2025-26, American Banker Innovation of the Year 2025. | H4: increase.com/pricing. NOTE: partner Grasshopper is being acquired by Enova (closing H2 2026) — continuity risk if routed there. | J4: Not started
A5: Astra | B5: 2 - Rails | C5: Instant disbursement API | D5: Purpose-built for lenders' funding legs — RTP, FedNow, Visa Direct, Mastercard Send. Complement to a bank/BaaS stack, not a substitute. | E5: N/A — rails layer, not a credit issuer. | F5: YES — multi-rail confirmed. | G5: Active, marketing directly to lending use cases. | H5: astrafi.com/for-lending | J5: Not started
A6: Column N.A. | B6: 2 - Possible | C6: Chartered bank as direct API | D6: Healthiest balance sheet in the sector. Confirmed sub-second RTP + FedNow reaching 75%+ of US bank accounts. | E6: Lending infra exists but skews commercial/warehouse. Consumer secured lending at your size unverified. | F6: YES — both confirmed, FRB case study exists. | G6: ~$153M 2025 revenue (up ~126% YoY), founder-owned, no outside investors. | H6: column.com | J6: Not started
A7: Dwolla | B7: 3 - Possible | C7: Payments orchestration | D7: RTP + FedNow with intelligent orchestration across both. Lists lending as a vertical, but that means disbursement/repayment rails, not credit issuance. | E7: No — rails only. | F7: YES — both, recently expanded. | G7: Active. | H7: dwolla.com | J7: Not started
A8: Modern Treasury | B8: 3 - Complement | C8: Ledger + orchestration | D8: Not a bank or credit issuer. Potentially useful reconciliation layer on top of an FBO structure — but you already run a real double-entry ledger, so likely unnecessary spend right now. | E8: None. | F8: FedNow supported. | G8: Active, recently launched a PSP product. | H8: moderntreasury.com | J8: Not started
A9: Unit | B9: 4 - Caution | C9: BaaS | D9: Right lending primitives on paper (charge cards, revolving credit, LOC) but health signals are stale and docs frame lending as business-purpose only. | E9: Listed, but consumer secured support unclear. | F9: UNVERIFIED. | G9: NO confirmed funding or health update since 2022-23. Reportedly declined to answer viability questions. Yellow flag for a multi-year furnishing relationship. | H9: unit.co | J9: Not started
A10: Bond (now FIS) | B10: 4 - Caution | C10: Embedded finance, inside FIS | D10: Literally lists a 'Consumer Secured Credit Card' — closest NAMED product match found. But now inside FIS's enterprise sales org. | E10: Named secured consumer product. | F10: UNVERIFIED. | G10: Parent (FIS) is stable. But enterprise sales cycles of 6-12+ months would consume your entire runway. | H10: bond.tech | J10: Not started
A11: BureauRelay (Switch Labs) | B11: 1 - Furnishing | C11: Metro 2 furnishing vendor | D11: Only startup-shaped furnishing pricing found. Published tiers with API access — ~$29/mo at 1,000 records, ~$49/mo at 10,000. | E11: N/A — furnishing only. | F11: N/A | G11: Active. | H11: bureaurelay.com. ASK EVERY BANK/BAAS FIRST whether furnishing is bundled — it may make this unnecessary. | J11: Not started
A12: Bloom Credit | B12: 2 - Furnishing | C12: Metro 2 furnishing vendor | D12: Enterprise-credible name if investor optics matter. Fully managed furnishing to all 3 bureaus with 700+ validation checks. | E12: N/A — furnishing only. | F12: N/A | G12: Active. | H12: bloomcredit.io/products/furnishment. Pricing unpublished, heavier sales lift. | J12: Not started
A13: EXAMPLE ROW - delete me | B13: 1 - Lead | C13: Example platform | D13: Example of the expected format — replace or delete once you start. | E13: Yes. | F13: Unverified. | G13: Active. | H13: example.com | J13: Not started

Sheet Track 3 - CDFI MDI
A1: Institution | B1: Priority | C1: Type | D1: Geography / Field of membership | E1: Why them — the hook | F1: ITIN program | G1: Fintech track record | H1: How to make contact | I1: Owner | J1: Status | K1: Last Contact | L1: Next Step | M1: Next Step Date | N1: Notes
A2: Sunrise Banks, N.A. | B2: 1 - Lead | C2: National bank · CDFI · B Corp | D2: Nationwide — no FOM restriction (banks aren't subject to NCUA rules). | E2: Spans Track 1 and Track 3. Self Financial credit-builder precedent PLUS a real ITIN program PLUS a working fintech BD function. Nothing else on this list has all three. | F2: YES — Pathway2Home ITIN mortgage program. | G2: Extensive: Self Financial, Lili, Usio, Remitly Passbook. | H2: sunrisebanks.com/fintech-partnerships · 844-786-5600 | J2: Not started
A3: Ponce Bank | B3: 2 - Strong | C3: National bank · CDFI + MDI | D3: NYC metro primarily. No FOM restriction. | E3: Dual CDFI + MDI — fewer than 40 US banks hold both. Founded 1960 by Puerto Rican migrants, majority Spanish-speaking staff. Best brand fit after Sunrise. | F3: Not confirmed — plausible given founding community. Ask. | G3: Tech-forward BD appetite (sidecar core partnership, BNY Mentor-Protégé) but NO confirmed BaaS program. Would be a build. | H3: poncebank.com — no fintech BD page; likely needs exec-level outreach. | J3: Not started
A4: Spring Bank | B4: 2 - Strong | C4: Bank · CDFI · B Corp · CDBA member | D4: Bronx, NY. No FOM restriction. | E4: Has its own credit-builder loan product — institutional comfort with the exact mechanic you're proposing. | F4: Not confirmed. Ask. | G4: Not confirmed. | H4: springbankny.com · also reachable via CDBA | J4: Not started
A5: Self-Help Federal Credit Union | B5: 3 - Possible | C5: CDFI credit union | D5: CA, CT, IL, SC, WA, WI (44 branches) + NC/SC via the state-chartered arm. NOT nationwide. | E5: Extraordinary catalog alignment — already offers BOTH an 'Immigration Loan' and a 'CreditBuilder Loan'. But no fintech-facing infrastructure at all. | F5: YES — named Immigration Loans and Dreamer Medical School Loans. | G5: None found. Historically an originate-and-hold balance-sheet lender, not a sponsor. | H5: self-helpfcu.org — needs exec/community-development outreach. | J5: Not started
A6: Latino Community Credit Union | B6: 3 - Possible | C6: State CU (NC) · CDFI · Juntos Avanzamos | D6: NC ONLY despite marketing copy implying open national eligibility. ~$1.05B assets. FOM discrepancy needs direct verification. | E6: Arguably the best brand fit on the entire list. But geographically constrained and no BaaS capability. | F6: YES — core to their model; requires SSN or ITIN for membership. | G6: Core/digital upgrades only (Jack Henry, Lumin Digital). Not a BaaS program. | H6: latinoccu.org — best used as a reference or an Inclusiv intro target. | J6: Not started
A7: Carver Federal Savings Bank | B7: 4 - Low | C7: MDI (Black-owned) · CDFI | D7: Harlem, NY. No FOM restriction. | E7: Demonstrated, CEO-championed appetite for outsourced lending tech (Upstart Referral Network, Moody's CreditLens). Real execution capability. | F7: Not confirmed. | G7: YES — Upstart partnership is a genuine precedent. | H7: carverbank.com — exec office outreach. | J7: Not started
A8: Guadalupe Credit Union | B8: 4 - Low | C8: CDFI credit union | D8: SEVEN New Mexico counties only. Rules out a nationwide product via direct membership. | E8: High cultural fit, too small and narrow to be a primary partner. Pilot or reference only. | F8: YES — accepts ITIN and Matrícula Consular for membership. | G8: None found. | H8: guadalupecu.org | J8: Not started
A9: NETWORK: NBA MDI ConnectTech | B9: 1 - Channel | C9: Formal matchmaking program | D9: National. | E9: National Bankers Association + Alliance for Innovative Regulation + Inclusiv, funded by Visa. A multi-year 'test and learn' program explicitly designed to connect fintechs with MDIs. The most structured intro channel found anywhere. | F9: N/A | G9: N/A — this IS the fintech channel. | H9: 202-588-5432 · nationalbankers.org strategic partner form · regulationinnovation.org/mdi-connecttech-initiative | J9: Not started
A10: NETWORK: Inclusiv / Juntos Avanzamos | B10: 1 - Channel | C10: CDFI CU network + designation | D10: 167+ designated credit unions across 34 states serving Hispanic/immigrant communities. | E10: Source additional candidates AND sanity-check the FBO vs. field-of-membership question with people who work it daily. | F10: N/A | G10: N/A | H10: juntosavanzamos@inclusiv.org · (212) 809-1850 | J10: Not started
A11: NETWORK: CDBA | B11: 2 - Channel | C11: CDFI bank trade association | D11: National. | E11: Trade association for CDFI-certified banks — Spring Bank, Southern Bancorp, City First all members. Peer Forum ran June 2026; watch for 2027 and ask about non-member participation. | F11: N/A | G11: N/A | H11: cdbanks.org | J11: Not started
A12: NETWORK: OFN | B12: 2 - Channel | C12: CDFI trade association | D12: National. | E12: Launched an Innovation Council and Capital Solutions Accelerator in 2026 — possible fintech-CDFI matchmaking entry point. CDFI Locator tool for sourcing. | F12: N/A | G12: N/A | H12: ofn.org/cdfi-locator | J12: Not started
A13: EXAMPLE ROW - delete me | B13: 1 - Lead | C13: Bank · CDFI | D13: Nationwide | E13: Example of the expected format — replace or delete once you start. | F13: Unknown. | G13: None found. | H13: example.org | J13: Not started

Sheet Do Not Approach
A1: Institution | B1: Problem | C1: Detail | D1: Revisit?
A2: Evolve Bank & Trust | B2: Active Federal Reserve cease-and-desist | C2: C&D since 14 June 2024, still active as of Aug 2026. The bank at the center of the Synapse collapse — frozen/lost customer funds, ongoing litigation. Also suffered a LockBit ransomware breach (~33TB exposed). | D2: No. Reputational and operational risk too high regardless of fit.
A3: Lineage Bank | B3: Second active FDIC consent order | C3: Ordered to terminate fintech partnerships Jan 2024 after growing $27M → $300M in assets. A SECOND active order dated 24 June 2026. The regulator is actively pushing this bank out of BaaS. | D3: No.
A4: Sutton Bank | B4: Active FDIC BSA/AML consent order | C4: Order since Feb 2024. Still signing card deals, so it hasn't stopped business — but an open BSA/AML order is the single worst regulatory profile to pair with an ITIN-heavy customer base in the current climate. | D4: Only if the order is confirmed terminated.
A5: Mode Eleven Bancorp | B5: Voluntarily exited fintech sponsorship | C5: Fed action March 2024, then exited the business entirely. Confirmed. | D5: No.
A6: Cross River Bank | B6: Active FDIC fair-lending consent order — but nuanced | C6: Order since March 2023. NOT a clean avoid: Cross River sponsors Común, a Hispanic-immigrant fintech with positioning close to yours. Also large ($20B+) and likely priced for bigger partners. | D6: Deprioritize as a lead, but the Común precedent makes it worth a call if other doors close.
A7: Community Federal Savings Bank | B7: NEW OCC consent order April 2026 | C7: AML/BSA failures: auto-closed a very high percentage of suspicious-activity alerts, weak due diligence on foreign financial institutions, understaffing. Second enforcement action (first 2020). Sponsors Wise and Común — relevant to cross-border fintechs, which makes this directly cautionary for you. | D7: No — but note it as the pattern to screen for: a small bank scaling fintech volume past its compliance capacity.
A8: Solid Financial Technologies | B8: DEAD — Chapter 11, liquidated | C8: Filed April 2025, liquidation plan confirmed Nov 2025. Common equity wiped out. Lost its sponsor bank (Lewis & Clark) in Aug 2024. Do not approach. | D8: No.
A9: Synapse | B9: DEAD — bankrupt, depositor shortfall unresolved | C9: Chapter 11 April 2024. ~$65-95M in depositor funds still unresolved a year later. The foundational cautionary tale of the sector. | D9: No.
A10: Lewis & Clark Bank | B10: Status unknown / likely disrupted | C10: Its one publicized BaaS relationship was via Solid, which went bankrupt. No evidence of program status since. Insufficient information. | D10: Only with direct confirmation.
A11: Marqeta / Galileo | B11: Wrong shape — card issuing processors | C11: Both assume a card rail. You explicitly need no card or BIN program. They appear in every BaaS comparison list, so flagging to prevent a wrong turn. | D11: Only if the product adds a card.
A12: Nova Credit | B12: Miscategorized — NOT a furnishing service | C12: Translates foreign credit files into US-readable scores. Does not solve Metro 2 bureau reporting. BUT potentially valuable later as an underwriting signal for LATAM immigrants with home-country credit history. | D12: Yes — as an underwriting input, not a furnishing solution.

Sheet Outreach Channels
A1: Channel | B1: Type | C1: Priority | D1: Timing / Deadline | E1: Cost | F1: Why it matters | G1: Action | H1: Owner | I1: Status | J1: Applied / Registered? | K1: Notes
A2: ICBA ThinkTECH Accelerator | B2: Accelerator | C2: 1 - Do this first | D2: Next cohort January 2027. Rolling applications via F6S — apply now. | E2: Free | F2: Built specifically to put early-stage fintechs in front of hundreds of community bank executives — demo days, 1:1s, ICBA LIVE exposure. ~6 companies per cohort, 150+ alumni (Alkami, Sardine, Finzly). This is the single highest-value action available to a company with no warm intros. | G2: Apply. Contact Pierce Sloan, Pierce.Sloan@icba.org | I2: Not started
A3: Plug and Play Inclusive Fintech Accelerator | B3: Accelerator | C3: 1 - High | D3: Cohort 3 timing unconfirmed — monitor. | E3: Free / non-dilutive | F3: Run with Visa. Explicitly targets diverse founders building inclusive fintech; past cohorts included Latinx and immigrant-focused products. Facilitated 300+ financial-institution introductions in cohort 2. Most mission-aligned program found. | G3: Watch for the next cohort opening and apply immediately. | I3: Not started
A4: UBA AI-Native Banking & Fintech Conference | B4: Conference | C4: 1 - High | D4: 29 September 2026 — six weeks out | E4: Not published — inquire | F4: Utah Bankers Association, co-organized with Spring Labs. Ken Garff University Club, Salt Lake City. The one dated, verified, in-state opportunity — and Utah has the country's highest concentration of fintech-partner industrial banks. | G4: Register now. utah.bank/events | I4: Not started
A5: Money20/20 USA | B5: Conference | C5: 2 - Worthwhile | D5: 18-21 October 2026, Las Vegas | E5: $1,545 Early Stage Startup Pass | F5: Requires live product, <3 years incorporated, <$5M raised — you likely qualify. Founder accounts report genuine executive relationship-building, not immediate deals. Attendee mix skews payments/card-network rather than community-bank BD. | G5: Book the Early Stage pass if budget allows. us.money2020.com/attend/passes | I5: Not started
A6: Fintech Meetup | B6: Conference | C6: 2 - Worthwhile | D6: Historically March — 2027 dates not yet published | E6: $1,495 Startup pass | F6: Distinctive software-matched 1:1 meeting system — 60,000+ scheduled meetings in 2025. Structurally better for actually getting meetings than booth-wandering. | G6: Watch for 2027 dates. fintechmeetup.com | I6: Not started
A7: ICBA LIVE | B7: Conference | C7: 3 - Conditional | D7: 1-4 March 2027, Las Vegas | E7: $1,675-2,575 (bank pricing; vendor tier unconfirmed) | F7: Where community bank CEOs and CFOs go in volume — most decision-makers per dollar of any event researched. But no fintech/vendor pricing tier was published. | G7: Better attended via the ThinkTECH pipeline than paid cold. Inquire about vendor pricing. | I7: Not started
A8: Sponsor-bank consultants | B8: Advisory | C8: 3 - Conditional | D8: Anytime | E8: None publish rates — expect five figures for a retainer | F8: Fintech2Bank (led by ex-WebBank/Axos CEO), Fraxtional (claims pre-qualified bank introductions), FS Vector (chartering/licensing). Credible but expensive relative to your cash position. | G8: Buy a short paid diligence-readiness review, NOT a retainer. Qualifying question: 'do you have a live relationship with a bank currently serving ITIN customers?' That's the only thing they offer that you can't do yourself. | I8: Not started
A9: Stena Center for Financial Technology | B9: Ecosystem | C9: 3 - Local | D9: Annual Fintech Xchange conference — dates unconfirmed | E9: Unknown | F9: University of Utah, funded by up to $65M from the Stena Foundation. Convenes company executives, regulators and lawmakers. The most plausible academic-adjacent venue in Utah. | G9: Email directly for Fintech Xchange dates. fintech.utah.edu | I9: Not started
A10: Utah DFI — Supervisor of Industrial Banks | B10: Regulator | C10: 3 - Local | D10: Anytime | E10: Free | F10: No industrial-bank or fintech events on their calendar (confirmed), but a direct line to the people who supervise the banks you're targeting. Useful for understanding posture, not for introductions. | G10: (801) 538-8830 · dfi@utah.gov | I10: Not started
A11: EXAMPLE ROW - delete me | B11: Conference | C11: 1 - High | D11: Some date 2026 | E11: $0 | F11: Example of the expected format — replace or delete once you start. | G11: Do the thing | I11: Not started

Sheet First Call Questions
A1: # | B1: Question | C1: Why it matters | D1: Kills the deal if...
A2: 1 | B2: Do you onboard ITIN-only customers today, and has your posture changed since the May 2026 executive order? | C2: ASK THIS FIRST, ALWAYS. Not one bank or platform in the entire research sweep publicly states its ITIN policy. It cannot be screened in advance, and it's the thing most likely to end a conversation in month four instead of minute four. | D2: They say no, or they hedge without a concrete example of an ITIN customer today.
A3: 2 | B3: Would you support an FBO/omnibus deposit structure with Puente maintaining the sub-ledger, rather than individual DDAs? | C3: This is the version that lets them avoid onboarding thousands of ITIN customers directly. It's your best offer to them, not a concession. | D3: They require individual DDAs AND won't take ITIN — that combination is unworkable.
A4: 3 | B4: Can you issue an open-end line of credit in the consumer's name, secured by a deposit you hold, with NO card rail? | C4: Most secured credit infrastructure assumes a card. Yours doesn't. This is a genuine simplification you should sell, but it's also non-standard. | D4: Their secured credit product cannot be decoupled from card issuance.
A5: 4 | B5: Do you support RTP and/or FedNow for funding, and what's the per-transaction cost to us? | C5: Irrevocable settlement is what makes 'fully secured' true. Network cost is $0.045; Increase publishes $2.50. Anything far above that is markup you should negotiate. | D5: ACH only. A 60-day return window leaves your collateral exposed after the remittance is gone.
A6: 5 | B6: Is credit bureau furnishing bundled, or do we need a separate vendor? | C6: Longest lead time after the bank itself, and it's your core value proposition. Bundling could eliminate a whole vendor category. | D6: Nothing — but the answer changes your build plan and timeline materially.
A7: 6 | B7: What's your minimum program size, and will you work with a pre-revenue company? | C7: Ask early. Several banks reject 12-18 applicants per acceptance specifically for being too small. Better to hear it on call one. | D7: They have a volume or revenue floor you can't clear within your runway.
A8: 7 | B8: What's your current regulatory standing, and have you had any enforcement action in the last three years? | C8: You'll verify independently via FDIC and OCC databases — but ask anyway. How they answer tells you as much as what they answer. | D8: Active BSA/AML order. Worst possible pairing with an ITIN-heavy customer base.
A9: 8 | B9: Realistically, how long from today to first originated loan? | C9: You have 6-12 months. A 12-month diligence cycle consumes all of it. | D9: Longer than your runway.
A10: 9 | B10: Who else in our category do you sponsor, and can we reference-check with them? | C10: Reference-checking existing fintech partners is standard and revealing. A bank that won't facilitate it is telling you something. | D10: They refuse, or existing partners report poor responsiveness.
A11: 10 | B11: What does your diligence package require, and what's your compliance expectation of us? | C11: Sets up your bank-ready package and surfaces gaps early. Lead your answer with your in-house compliance officer — most seed companies don't have one. | D11: Nothing — but it tells you what to build.

Sheet Dashboard
A1: Puente — Bank Partnership Pipeline
A2: Counts update automatically from the Status column on each track tab.
A4: Status | B4: Track 1 — Program Banks | C4: Track 2 — Middleware | D4: Track 3 — CDFI / MDI | E4: Total
A5: Not started | B5: =COUNTIF('Track 1 - Program Banks'!$J$2:$J$14,$A5) -> 13 | C5: =COUNTIF('Track 2 - Middleware'!$J$2:$J$13,$A5) -> 12 | D5: =COUNTIF('Track 3 - CDFI MDI'!$J$2:$J$13,$A5) -> 12 | E5: =SUM(B5:D5) -> 37
A6: Researching | B6: =COUNTIF('Track 1 - Program Banks'!$J$2:$J$14,$A6) -> 0 | C6: =COUNTIF('Track 2 - Middleware'!$J$2:$J$13,$A6) -> 0 | D6: =COUNTIF('Track 3 - CDFI MDI'!$J$2:$J$13,$A6) -> 0 | E6: =SUM(B6:D6) -> 0
A7: Email sent | B7: =COUNTIF('Track 1 - Program Banks'!$J$2:$J$14,$A7) -> 0 | C7: =COUNTIF('Track 2 - Middleware'!$J$2:$J$13,$A7) -> 0 | D7: =COUNTIF('Track 3 - CDFI MDI'!$J$2:$J$13,$A7) -> 0 | E7: =SUM(B7:D7) -> 0
A8: Follow-up sent | B8: =COUNTIF('Track 1 - Program Banks'!$J$2:$J$14,$A8) -> 0 | C8: =COUNTIF('Track 2 - Middleware'!$J$2:$J$13,$A8) -> 0 | D8: =COUNTIF('Track 3 - CDFI MDI'!$J$2:$J$13,$A8) -> 0 | E8: =SUM(B8:D8) -> 0
A9: Call scheduled | B9: =COUNTIF('Track 1 - Program Banks'!$J$2:$J$14,$A9) -> 0 | C9: =COUNTIF('Track 2 - Middleware'!$J$2:$J$13,$A9) -> 0 | D9: =COUNTIF('Track 3 - CDFI MDI'!$J$2:$J$13,$A9) -> 0 | E9: =SUM(B9:D9) -> 0
A10: In discussion | B10: =COUNTIF('Track 1 - Program Banks'!$J$2:$J$14,$A10) -> 0 | C10: =COUNTIF('Track 2 - Middleware'!$J$2:$J$13,$A10) -> 0 | D10: =COUNTIF('Track 3 - CDFI MDI'!$J$2:$J$13,$A10) -> 0 | E10: =SUM(B10:D10) -> 0
A11: Diligence | B11: =COUNTIF('Track 1 - Program Banks'!$J$2:$J$14,$A11) -> 0 | C11: =COUNTIF('Track 2 - Middleware'!$J$2:$J$13,$A11) -> 0 | D11: =COUNTIF('Track 3 - CDFI MDI'!$J$2:$J$13,$A11) -> 0 | E11: =SUM(B11:D11) -> 0
A12: Term sheet | B12: =COUNTIF('Track 1 - Program Banks'!$J$2:$J$14,$A12) -> 0 | C12: =COUNTIF('Track 2 - Middleware'!$J$2:$J$13,$A12) -> 0 | D12: =COUNTIF('Track 3 - CDFI MDI'!$J$2:$J$13,$A12) -> 0 | E12: =SUM(B12:D12) -> 0
A13: Won | B13: =COUNTIF('Track 1 - Program Banks'!$J$2:$J$14,$A13) -> 0 | C13: =COUNTIF('Track 2 - Middleware'!$J$2:$J$13,$A13) -> 0 | D13: =COUNTIF('Track 3 - CDFI MDI'!$J$2:$J$13,$A13) -> 0 | E13: =SUM(B13:D13) -> 0
A14: Passed - us | B14: =COUNTIF('Track 1 - Program Banks'!$J$2:$J$14,$A14) -> 0 | C14: =COUNTIF('Track 2 - Middleware'!$J$2:$J$13,$A14) -> 0 | D14: =COUNTIF('Track 3 - CDFI MDI'!$J$2:$J$13,$A14) -> 0 | E14: =SUM(B14:D14) -> 0
A15: Passed - them | B15: =COUNTIF('Track 1 - Program Banks'!$J$2:$J$14,$A15) -> 0 | C15: =COUNTIF('Track 2 - Middleware'!$J$2:$J$13,$A15) -> 0 | D15: =COUNTIF('Track 3 - CDFI MDI'!$J$2:$J$13,$A15) -> 0 | E15: =SUM(B15:D15) -> 0
A16: No response | B16: =COUNTIF('Track 1 - Program Banks'!$J$2:$J$14,$A16) -> 0 | C16: =COUNTIF('Track 2 - Middleware'!$J$2:$J$13,$A16) -> 0 | D16: =COUNTIF('Track 3 - CDFI MDI'!$J$2:$J$13,$A16) -> 0 | E16: =SUM(B16:D16) -> 0
A17: TOTAL TARGETS | B17: =SUM(B5:B16) -> 13 | C17: =SUM(C5:C16) -> 12 | D17: =SUM(D5:D16) -> 12 | E17: =SUM(E5:E16) -> 37
A20: ACTIVE PIPELINE (contacted, not yet closed out) | B20: =SUM(B7:B12)+SUM(C7:C12)+SUM(D7:D12) -> 0
A22: NEXT ACTIONS
A23: 1. Apply to ICBA ThinkTECH — free, and the highest-yield action available to you. Pierce.Sloan@icba.org
A24: 2. Register for the UBA fintech conference, 29 Sept 2026, Salt Lake City — six weeks out, in your city.
A25: 3. Email Sunrise Banks referencing the Self Financial precedent explicitly.
A26: 4. Email Academy Bank referencing the Atlas ITIN + Spanish-language partnership explicitly.
A27: 5. Call Synctera and ask whether CHARGE_SECURED can be decoupled from a card rail.
A28: 6. Decide SSN-first vs. ITIN-from-launch. Highest-stakes open decision — see strategy doc §0.3.
A29: 7. Decide the furnishing path — longest lead time after the bank itself.
A30: 8. Re-verify every consent order at orders.fdic.gov and apps.occ.gov/EASearch before any outreach.
